async_sched/__init__.py
async_sched/__meta__.py
async_sched/schedule.py
async_sched/utils.py
async_sched/__pycache__/__init__.cpython-38.pyc
async_sched/__pycache__/schedule.cpython-38.pyc
async_sched/__pycache__/utils.cpython-38.pyc
async_sched/client/__init__.py
async_sched/client/__main__.py
async_sched/client/client.py
async_sched/client/quit_server.py
async_sched/client/request_schedules.py
async_sched/client/run_command.py
async_sched/client/schedule_command.py
async_sched/client/stop_schedule.py
async_sched/client/update_server.py
async_sched/client/__pycache__/__init__.cpython-38.pyc
async_sched/client/__pycache__/__main__.cpython-38.pyc
async_sched/client/__pycache__/client.cpython-38.pyc
async_sched/client/__pycache__/quit_server.cpython-38.pyc
async_sched/client/__pycache__/request_schedules.cpython-38.pyc
async_sched/client/__pycache__/run_command.cpython-38.pyc
async_sched/client/__pycache__/schedule_command.cpython-38.pyc
async_sched/client/__pycache__/stop_schedule.cpython-38.pyc
async_sched/client/__pycache__/update_server.cpython-38.pyc
async_sched/server/__init__.py
async_sched/server/__main__.py
async_sched/server/client.py
async_sched/server/messages.py
async_sched/server/srv.py
async_sched/server/__pycache__/__init__.cpython-38.pyc
async_sched/server/__pycache__/__main__.cpython-38.pyc
async_sched/server/__pycache__/client.cpython-38.pyc
async_sched/server/__pycache__/messages.cpython-38.pyc
async_sched/server/__pycache__/srv.cpython-38.pyc
async_sched-1.2.5.dist-info/LICENSE
async_sched-1.2.5.dist-info/METADATA
async_sched-1.2.5.dist-info/WHEEL
async_sched-1.2.5.dist-info/top_level.txt
async_sched-1.2.5.dist-info/RECORD
